[
  {
    "circular_no": "44",
    "category": "T&S",
    "title": "Commencement of Futures Trading in Gold Ten July 2026 Contract",
    "link": "https://www.mcxindia.com/docs/default-source/circulars/english/2026/january/circular---044---2026.pdf?sfvrsn=14d83a9e_0"
  },
  {
    "circular_no": "43",
    "category": "T&S",
    "title": "Commencement of Futures Trading in Gold Petal July 2026 Contract",
    "link": "https://www.mcxindia.com/docs/default-source/circulars/english/2026/january/circular---043---2026.pdf?sfvrsn=ced83a9e_0"
  },
  {
    "circular_no": "42",
    "category": "T&S",
    "title": "Commencement of Futures Trading in Gold Guinea July 2026 Contract",
    "link": "https://www.mcxindia.com/docs/default-source/circulars/english/2026/january/circular---042---2026.pdf?sfvrsn=ead83a9e_0"
  },
  {
    "circular_no": "41",
    "category": "T&S",
    "title": "Commencement of Futures Trading in Gold Mini August 2026 Contract",
    "link": "https://www.mcxindia.com/docs/default-source/circulars/english/2026/january/circular---041---2026.pdf?sfvrsn=b6d83a9e_0"
  },
  {
    "circular_no": "40",
    "category": "T&S",
    "title": "Commencement of Futures Trading in Gold February 2027 Contract",
    "link": "https://www.mcxindia.com/docs/default-source/circulars/english/2026/january/circular---040---2026.pdf?sfvrsn=ccd93a9e_0"
  },
  {
    "circular_no": "39",
    "category": "MCXCCL",
    "title": "Schedule of Client Collateral Segregation Reporting on account of Special Live Trading Session on Sunday, February 01, 2026 - Presentation of Union Budget",
    "link": "https://www.mcxindia.com/docs/default-source/circulars/english/2026/january/circular-039-2026.pdf?sfvrsn=d8eb3a9e_0"
  }
]