[
  {
    "date": "April 09, 2026",
    "department": "Mutual Fund",
    "subject": "Availability of Choice Nifty Next 50 Index Fund for ongoing transactions on NSE MF Invest Platform",
    "circular_ref": "NSE/NMF/73664",
    "link": "https://nsearchives.nseindia.com/content/circulars/NMF73664.pdf"
  },
  {
    "date": "April 09, 2026",
    "department": "Mutual Fund",
    "subject": "Availability of Choice Nifty 50 Index Fund for ongoing transactions on NSE MF Invest Platform",
    "circular_ref": "NSE/NMF/73648",
    "link": "https://nsearchives.nseindia.com/content/circulars/NMF73648.pdf"
  }
]